django_ai/__init__.py
django_ai/apps.py
django_ai/manage.py
django_ai/base/__init__.py
django_ai/base/admin.py
django_ai/base/apps.py
django_ai/base/models.py
django_ai/base/urls.py
django_ai/base/utils.py
django_ai/base/views.py
django_ai/base/migrations/0001_initial.py
django_ai/base/migrations/__init__.py
django_ai/base/templates/base/admin/mixed_inlines_change_form.html
django_ai/base/templates/base/snippets/ai_actions.html
django_ai/base/templatetags/__init__.py
django_ai/base/templatetags/admin_extras.py
django_ai/bayesian_networks/__init__.py
django_ai/bayesian_networks/admin.py
django_ai/bayesian_networks/apps.py
django_ai/bayesian_networks/bayespy_constants.py
django_ai/bayesian_networks/models.py
django_ai/bayesian_networks/scratchpad.py
django_ai/bayesian_networks/tests.py
django_ai/bayesian_networks/urls.py
django_ai/bayesian_networks/utils.py
django_ai/bayesian_networks/views.py
django_ai/bayesian_networks/migrations/__init__.py
django_ai/bayesian_networks/static/css/admin/bayesian_networks.css
django_ai/bayesian_networks/static/js/admin/bayesian_networks.js
django_ai/bayesian_networks/templates/admin/bayesian_networks/bayesiannetwork/change_form.html
django_ai/bayesian_networks/templates/admin/bayesian_networks/bayesiannetwork/snippets/cm_table.html
django_ai/bayesian_networks/templatetags/__init__.py
django_ai/bayesian_networks/templatetags/utils.py
django_ai/django_ai/__init__.py
django_ai/django_ai/settings.py
django_ai/django_ai/urls.py
django_ai/django_ai/wsgi.py
django_ai/examples/__init__.py
django_ai/examples/admin.py
django_ai/examples/apps.py
django_ai/examples/forms.py
django_ai/examples/metrics.py
django_ai/examples/models.py
django_ai/examples/tests.py
django_ai/examples/urls.py
django_ai/examples/views.py
django_ai/examples/migrations/0001_initial.py
django_ai/examples/migrations/0002_student_avg1.py
django_ai/examples/migrations/0003_populate_userinfo.py
django_ai-0.0.2.1.dist-info/DESCRIPTION.rst
django_ai-0.0.2.1.dist-info/METADATA
django_ai-0.0.2.1.dist-info/RECORD
django_ai-0.0.2.1.dist-info/WHEEL
django_ai-0.0.2.1.dist-info/metadata.json
django_ai-0.0.2.1.dist-info/top_level.txt
