Metadata-Version: 2.0
Name: django-ai
Version: 0.0.2.1
Summary: Artificial Intelligence for Django
Home-page: https://github.com/math-a3k/django-ai
Author: Rodrigo Gadea
Author-email: matematica.a3k@gmail.com
License: LGPLv3
Keywords: django-ai
Platform: UNKNOWN
Classifier: Development Status :: 5 - Production/Stable
Classifier: Framework :: Django
Classifier: Framework :: Django :: 1.11
Classifier: Intended Audience :: Developers
Classifier: License :: OSI Approved :: GNU Lesser General Public License v3 or later (LGPLv3+)
Classifier: Natural Language :: English
Classifier: Programming Language :: Python :: 3
Classifier: Programming Language :: Python :: 3.5
Classifier: Topic :: Scientific/Engineering :: Artificial Intelligence
Classifier: Topic :: Scientific/Engineering :: Mathematics
Classifier: Topic :: Software Development :: Libraries :: Application Frameworks
Requires-Dist: Django (<2.1,>=1.11)
Requires-Dist: Pillow (==4.2.1)
Requires-Dist: bayespy (==0.5.6)
Requires-Dist: django-nested-admin (==3.0.20)
Requires-Dist: django-picklefield (==1.0.0)
Requires-Dist: graphviz (==0.6)
Requires-Dist: jsonfield (==2.0.2)
Requires-Dist: numpy (<1.14)
Requires-Dist: scikit-learn (>=0.19.1)
